miniwalk-0.1.0.dist-info/METADATA
miniwalk-0.1.0.dist-info/WHEEL
miniwalk-0.1.0.dist-info/entry_points.txt
miniwalk-0.1.0.dist-info/licenses/LICENSE
miniwalk/__init__.py
miniwalk/commands/__init__.py
miniwalk/commands/ins2dup.py
miniwalk/commands/mod.py
miniwalk/commands/pr_graph_overlap.py
miniwalk/commands/pr_graph_overlap_output4graph.py
miniwalk/commands/pr_graph_overlap_output4graph_svimasm.py
miniwalk/commands/pr_graph_overlap_svimasm.py
miniwalk/commands/pr_manta_overlap.py
miniwalk/commands/pr_manta_overlap_output4graph.py
miniwalk/commands/pr_manta_overlap_output4graph_svimasm.py
miniwalk/commands/pr_manta_overlap_svimasm.py
miniwalk/commands/ref.py
miniwalk/main.py
miniwalk-0.1.0.dist-info/RECORD
