Metadata-Version: 2.1
Name: miniwalk
Version: 0.1.0
Summary: miniwalk is a tool for genotyping SVs from minigraph .gfa graphs
Author-Email: aleixcanalda <aleix98@hotmail.com>
License: MIT
Requires-Python: >=3.10
Requires-Dist: pandas
Requires-Dist: Bio
Requires-Dist: numpy
